glocaltokens/__init__.py
glocaltokens/client.py
glocaltokens/const.py
glocaltokens/py.typed
glocaltokens/scanner.py
glocaltokens/types.py
glocaltokens/utils/__init__.py
glocaltokens/utils/logs.py
glocaltokens/utils/network.py
glocaltokens/utils/token.py
glocaltokens-0.7.6.dist-info/METADATA
glocaltokens-0.7.6.dist-info/WHEEL
glocaltokens-0.7.6.dist-info/licenses/LICENSE
glocaltokens-0.7.6.dist-info/RECORD
