Metadata-Version: 2.4
Name: glocaltokens
Version: 0.7.6
Summary: Tool to extract Google device local authentication tokens in Python
Project-URL: Homepage, https://github.com/leikoilja/glocaltokens
Project-URL: Bug Tracker, https://github.com/leikoilja/glocaltokens/issues
Project-URL: Release Notes, https://github.com/leikoilja/glocaltokens/releases
Author-email: Ilja Leiko <leikoilja@gmail.com>
License: MIT
License-File: LICENSE
Keywords: Authentication,Google,Google Home,LocalAuthenticationTokens
Classifier: Development Status :: 4 - Beta
Classifier: Intended Audience :: Developers
Classifier: License :: OSI Approved :: MIT License
Classifier: Operating System :: OS Independent
Classifier: Programming Language :: Python :: 3.9
Classifier: Programming Language :: Python :: 3.10
Classifier: Topic :: Software Development
Classifier: Typing :: Typed
Requires-Python: >=3.9
Requires-Dist: ghome-foyer-api>=1.2.2
Requires-Dist: gpsoauth>=2.0.0
Requires-Dist: grpcio>=1.72.1
Requires-Dist: requests>=2.32.4
Requires-Dist: simplejson>=3.20.1
Requires-Dist: zeroconf>=0.147.0
